petro_lingo/__init__.py
petro_lingo/database/__init__.py
petro_lingo/database/database.py
petro_lingo/drivers/__init__.py
petro_lingo/drivers/base_driver.py
petro_lingo/drivers/driver_ask.py
petro_lingo/drivers/driver_relogger.py
petro_lingo/drivers/driver_summary.py
petro_lingo/engine/__init__.py
petro_lingo/engine/engine.py
petro_lingo/model/__init__.py
petro_lingo/model/base_model.py
petro_lingo/model/chat_gpt.py
petro_lingo/model/inquirer.py
petro_lingo/model/model_factory.py
petro_lingo/model/relogger.py
petro_lingo/model/summarizer.py
petro_lingo/model/user.py
petro_lingo/shared/__init__.py
petro_lingo/shared/geoh5py_utils.py
petro_lingo/shared/utils.py
petro_lingo-assets/__init__.py
petro_lingo-assets/demo_petro_lingo.geoh5
petro_lingo-assets/test_petro_lingo.geoh5
petro_lingo-assets/test_petro_lingo.ipynb
petro_lingo-assets/uijsons/ask.ui.json
petro_lingo-assets/uijsons/relogger.ui.json
petro_lingo-assets/uijsons/summary.ui.json
petro_lingo-0.1.0a1.dist-info/LICENSE
petro_lingo-0.1.0a1.dist-info/METADATA
petro_lingo-0.1.0a1.dist-info/WHEEL
petro_lingo-0.1.0a1.dist-info/RECORD
