Metadata-Version: 2.1
Name: petro-lingo
Version: 0.1.0a1
Summary: Petro Lingo application
Home-page: https://mirageoscience.com
License: Proprietary
Author: Mira Geoscience
Author-email: support@mirageoscience.com
Requires-Python: >=3.10,<3.11
Classifier: Development Status :: 2 - Pre-Alpha
Classifier: Intended Audience :: Developers
Classifier: Intended Audience :: Science/Research
Classifier: License :: Other/Proprietary License
Classifier: Natural Language :: English
Classifier: Programming Language :: Python :: 3
Classifier: Programming Language :: Python :: 3.10
Classifier: Topic :: Database
Classifier: Topic :: Scientific/Engineering
Requires-Dist: geoh5py (>=0.9.0-alpha.4,<0.10.0)
Requires-Dist: numpy (>=1.23.5,<1.24.0)
Requires-Dist: openai (>=1.12.0,<1.13.0)
Requires-Dist: pandas (>=2.2.1,<2.3.0)
Requires-Dist: pydantic (>=2.6.3,<2.7.0)
Requires-Dist: scikit-learn (>=1.4.0,<1.5.0)
Requires-Dist: sentencepiece (>=0.1.99,<0.2.0)
Requires-Dist: tqdm (>=4.66.1,<4.67.0)
Requires-Dist: transformers (>=4.36.2,<4.37.0)
Project-URL: Documentation, https://petro-lingo.readthedocs.io/en/latest/
Project-URL: Repository, https://github.com/MiraGeoscience/petro-lingo
